AnyQt/QtCore.py
AnyQt/QtDBus.py
AnyQt/QtDesigner.py
AnyQt/QtGui.py
AnyQt/QtHelp.py
AnyQt/QtMacExtras.py
AnyQt/QtMultimedia.py
AnyQt/QtMultimediaWidgets.py
AnyQt/QtNetwork.py
AnyQt/QtOpenGL.py
AnyQt/QtPrintSupport.py
AnyQt/QtQml.py
AnyQt/QtQuick.py
AnyQt/QtSql.py
AnyQt/QtSvg.py
AnyQt/QtSvgWidgets.py
AnyQt/QtTest.py
AnyQt/QtWebChannel.py
AnyQt/QtWebEngineCore.py
AnyQt/QtWebEngineWidgets.py
AnyQt/QtWebKit.py
AnyQt/QtWebKitWidgets.py
AnyQt/QtWebSockets.py
AnyQt/QtWidgets.py
AnyQt/QtWinExtras.py
AnyQt/QtX11Extras.py
AnyQt/QtXml.py
AnyQt/QtXmlPatterns.py
AnyQt/__init__.py
AnyQt/_api.py
AnyQt/_compat.py
AnyQt/_ctypes.py
AnyQt/_fixes.py
AnyQt/importhooks.py
AnyQt/sip.py
AnyQt/uic.py
AnyQt/_backport/QtCore.py
AnyQt/_backport/QtDBus.py
AnyQt/_backport/QtDesigner.py
AnyQt/_backport/QtGui.py
AnyQt/_backport/QtHelp.py
AnyQt/_backport/QtMultimedia.py
AnyQt/_backport/QtNetwork.py
AnyQt/_backport/QtOpenGL.py
AnyQt/_backport/QtSql.py
AnyQt/_backport/QtSvg.py
AnyQt/_backport/QtTest.py
AnyQt/_backport/QtWebKit.py
AnyQt/_backport/QtXml.py
AnyQt/_backport/QtXmlPatterns.py
AnyQt/_backport/__init__.py
AnyQt/_backport/_utils.py
AnyQt/_backport/uic.py
anyqt-0.2.1.dist-info/licenses/LICENSE.txt
anyqt-0.2.1.dist-info/METADATA
anyqt-0.2.1.dist-info/WHEEL
anyqt-0.2.1.dist-info/top_level.txt
anyqt-0.2.1.dist-info/RECORD
