Metadata-Version: 2.4
Name: AnyQt
Version: 0.2.1
Summary: PyQt5/PyQt6 compatibility layer.
Home-page: https://github.com/ales-erjavec/anyqt
Author: Aleš Erjavec
Author-email: ales.erjavec@fri.uni-lj.si
License: GPLv3
Project-URL: Bug Reports, https://github.com/ales-erjavec/anyqt/issues
Project-URL: Source, https://github.com/ales-erjavec/anyqt
Project-URL: Documentation, https://anyqt.readthedocs.io/en/stable/
Keywords: GUI,PyQt4,PyQt5,PySide,PySide2,compatibility
Classifier: Development Status :: 1 - Planning
Classifier: Intended Audience :: Developers
Classifier: License :: OSI Approved :: GNU General Public License v3 (GPLv3)
Classifier: Operating System :: OS Independent
Classifier: Programming Language :: Python :: 2
Classifier: Programming Language :: Python :: 3
Requires-Python: >=3.6
License-File: LICENSE.txt
Dynamic: author
Dynamic: author-email
Dynamic: classifier
Dynamic: description
Dynamic: home-page
Dynamic: keywords
Dynamic: license
Dynamic: license-file
Dynamic: project-url
Dynamic: requires-python
Dynamic: summary
